serbot2/Util.py
serbot2/__init__.py
serbot2/config.py
serbot2/driving.py
serbot2/sensors.py
serbot2/LiDAR/__init__.py
serbot2/LiDAR/_lidar2d.so
serbot2/LiDAR/_rplidar.so
serbot2/LiDAR/lidar2d.py
serbot2/LiDAR/lidar2d_imp.py
serbot2/LiDAR/rplidar.py
serbot2/options/Analog.py
serbot2/options/CAN.py
serbot2/options/PGCA.py
serbot2/options/RGB.py
serbot2/options/Switch.py
serbot2/options/TPHG.py
serbot2/options/Thermopile.py
serbot2/options/ToF.py
serbot2/options/__init__.py
pop_serbot2-0.0.8.dist-info/METADATA
pop_serbot2-0.0.8.dist-info/WHEEL
pop_serbot2-0.0.8.dist-info/top_level.txt
pop_serbot2-0.0.8.dist-info/RECORD
